boox_annotation_parser/__init__.py
boox_annotation_parser/__main__.py
boox_annotation_parser/cli.py
boox_annotation_parser/parser.py
boox_annotation_parser/serializers.py
boox_annotation_parser/.mypy_cache/.gitignore
boox_annotation_parser/.mypy_cache/CACHEDIR.TAG
boox_annotation_parser/.mypy_cache/3.9/@plugins_snapshot.json
boox_annotation_parser/.mypy_cache/3.9/_ast.data.json
boox_annotation_parser/.mypy_cache/3.9/_ast.meta.json
boox_annotation_parser/.mypy_cache/3.9/_collections_abc.data.json
boox_annotation_parser/.mypy_cache/3.9/_collections_abc.meta.json
boox_annotation_parser/.mypy_cache/3.9/abc.data.json
boox_annotation_parser/.mypy_cache/3.9/abc.meta.json
boox_annotation_parser/.mypy_cache/3.9/argparse.data.json
boox_annotation_parser/.mypy_cache/3.9/argparse.meta.json
boox_annotation_parser/.mypy_cache/3.9/array.data.json
boox_annotation_parser/.mypy_cache/3.9/array.meta.json
boox_annotation_parser/.mypy_cache/3.9/ast.data.json
boox_annotation_parser/.mypy_cache/3.9/ast.meta.json
boox_annotation_parser/.mypy_cache/3.9/builtins.data.json
boox_annotation_parser/.mypy_cache/3.9/builtins.meta.json
boox_annotation_parser/.mypy_cache/3.9/codecs.data.json
boox_annotation_parser/.mypy_cache/3.9/codecs.meta.json
boox_annotation_parser/.mypy_cache/3.9/dataclasses.data.json
boox_annotation_parser/.mypy_cache/3.9/dataclasses.meta.json
boox_annotation_parser/.mypy_cache/3.9/datetime.data.json
boox_annotation_parser/.mypy_cache/3.9/datetime.meta.json
boox_annotation_parser/.mypy_cache/3.9/enum.data.json
boox_annotation_parser/.mypy_cache/3.9/enum.meta.json
boox_annotation_parser/.mypy_cache/3.9/genericpath.data.json
boox_annotation_parser/.mypy_cache/3.9/genericpath.meta.json
boox_annotation_parser/.mypy_cache/3.9/io.data.json
boox_annotation_parser/.mypy_cache/3.9/io.meta.json
boox_annotation_parser/.mypy_cache/3.9/mmap.data.json
boox_annotation_parser/.mypy_cache/3.9/mmap.meta.json
boox_annotation_parser/.mypy_cache/3.9/posix.data.json
boox_annotation_parser-0.1.2.dist-info/AUTHORS.rst
boox_annotation_parser-0.1.2.dist-info/LICENSE
boox_annotation_parser-0.1.2.dist-info/METADATA
boox_annotation_parser-0.1.2.dist-info/WHEEL
boox_annotation_parser-0.1.2.dist-info/entry_points.txt
boox_annotation_parser-0.1.2.dist-info/top_level.txt
boox_annotation_parser-0.1.2.dist-info/RECORD
