Metadata-Version: 2.1
Name: boox-annotation-parser
Version: 0.1.2
Summary: Parse annotation file exports from your Boox device, and transform them into JSON, YAML, or whatever you want.
Home-page: https://github.com/coddingtonbear/boox-annotation-parser
Author: Adam Coddington
Author-email: me@adamcoddington.net
License: MIT
Project-URL: Issue Tracker, https://github.com/coddingtonbear/boox-annotation-parser/issues
Platform: UNKNOWN
Classifier: Development Status :: 5 - Production/Stable
Classifier: Intended Audience :: Developers
Classifier: License :: OSI Approved :: MIT License
Classifier: Operating System :: Unix
Classifier: Operating System :: POSIX
Classifier: Operating System :: Microsoft :: Windows
Classifier: Programming Language :: Python
Classifier: Programming Language :: Python :: 3
Classifier: Programming Language :: Python :: 3 :: Only
Classifier: Programming Language :: Python :: 3.6
Classifier: Programming Language :: Python :: 3.7
Classifier: Programming Language :: Python :: 3.8
Classifier: Programming Language :: Python :: 3.9
Classifier: Programming Language :: Python :: Implementation :: CPython
Classifier: Programming Language :: Python :: Implementation :: PyPy
Classifier: Topic :: Utilities
Requires-Python: >=3.6
License-File: LICENSE
License-File: AUTHORS.rst
Requires-Dist: pyyaml (>=5.4.1)
